marknotion/__init__.py
marknotion/cli.py
marknotion/client.py
marknotion/md2notion.py
marknotion/notion2md.py
marknotion/types.py
marknotion-0.2.7.dist-info/METADATA
marknotion-0.2.7.dist-info/WHEEL
marknotion-0.2.7.dist-info/entry_points.txt
marknotion-0.2.7.dist-info/licenses/LICENSE
marknotion-0.2.7.dist-info/RECORD
