Metadata-Version: 2.4
Name: marknotion
Version: 0.2.7
Summary: Bidirectional Markdown ↔ Notion blocks converter
Project-URL: Homepage, https://github.com/li3p/marknotion
Project-URL: Repository, https://github.com/li3p/marknotion
Project-URL: Issues, https://github.com/li3p/marknotion/issues
Author-email: Libo <markdown@outlook.com>
License-Expression: MIT
License-File: LICENSE
Keywords: converter,markdown,notion
Classifier: Development Status :: 3 - Alpha
Classifier: Intended Audience :: Developers
Classifier: License :: OSI Approved :: MIT License
Classifier: Programming Language :: Python :: 3
Classifier: Programming Language :: Python :: 3.13
Requires-Python: >=3.13
Requires-Dist: click>=8.1.0
Requires-Dist: markdown-it-py>=3.0.0
Requires-Dist: mdit-py-plugins>=0.4.0
Requires-Dist: notion-client>=2.7.0
Requires-Dist: python-dotenv>=1.0.0
Provides-Extra: dev
Requires-Dist: pytest-cov>=4.0.0; extra == 'dev'
Requires-Dist: pytest>=8.0.0; extra == 'dev'
